[{"id_motorista":"1","nome":"Andreia","cpf":"111.222.85","dt_nascimento":"2018-02-15","model_car":"Camaro","sstatus":"1","sexo":"F"},{"id_motorista":"2","nome":"Savage","cpf":"gfhdfhg","dt_nascimento":"2018-02-08","model_car":"gdfhgdf","sstatus":"1","sexo":"M"},{"id_motorista":"3","nome":"dDDDDD","cpf":"DDDD","dt_nascimento":"2018-02-05","model_car":"DDDDDD","sstatus":"1","sexo":"M"},{"id_motorista":"4","nome":"AAAAA","cpf":"AAAA","dt_nascimento":"2018-02-09","model_car":"AAAAA","sstatus":"1","sexo":"M"},{"id_motorista":"5","nome":"firefox","cpf":"ffff","dt_nascimento":"2018-02-08","model_car":"ffff","sstatus":"1","sexo":"M"},{"id_motorista":"6","nome":"EDGE","cpf":"EEE","dt_nascimento":"2018-02-13","model_car":"EEEE","sstatus":"1","sexo":"M"},{"id_motorista":"7","nome":"OK","cpf":"AAA","dt_nascimento":"2018-02-08","model_car":"AAAA","sstatus":"1","sexo":"M"}]